{
  "_RecordName_": "SCItemManufacturer.Paint_L22_Wolf_white_grey_white_Spots_Logo",
  "_RecordId_": "bb3b6f7c-bbdb-4512-81a4-c11c2ed727a6",
  "_RecordTag_": "Unknown",
  "_RecordValue_": {
    "_Type_": "SCItemManufacturer",
    "Localization": {
      "_Type_": "SCItemLocalization",
      "Name": "@manufacturer_NameKRIG",
      "ShortName": "@LOC_EMPTY",
      "Description": "@manufacturer_DescKRIG",
      "displayFeatures": {
        "_Type_": "SCExtendedLocalizationLevelParams",
        "LogoSimplifiedWhite": "",
        "FrontendBackground": "",
        "History": "@LOC_EMPTY",
        "Callout1": "@LOC_EMPTY",
        "Callout2": "@LOC_EMPTY",
        "Callout3": "@LOC_EMPTY",
        "UIPriority": 0,
        "locationAudioPlayTrigger": {
          "_Type_": "GlobalResourceAudio",
          "audioTrigger": ""},
        "locationAudioStopTrigger": {
          "_Type_": "GlobalResourceAudio",
          "audioTrigger": ""}}},
    "Logo": "UI/SharedAssets/PaintColorLogos/Paint_L22_Alpha_Wolf_white_grey_white.tif",
    "LogoFullColor": "",
    "LogoSimplifiedWhite": "",
    "Code": "",
    "DashboardCanvasConfig": null,
    "BuildingBlocksStyle": null,
    "AudioManufacturerTag": null,
    "LightAmplification": null}}