{
  "_RecordName_": "InfractionDefinition.VehicleTowing",
  "_RecordId_": "f0b13e6a-012b-4411-8bc3-fd9682d8e918",
  "_RecordTag_": "Unknown",
  "_RecordValue_": {
    "_Type_": "InfractionDefinition",
    "name": "@Infractions_Name_047",
    "description": "@Infractions_Desc_047",
    "triggers": [
      "State_IllegalVehicleTowing"],
    "defaultParameters": {
      "_Type_": "InfractionParameters",
      "isFelony": 0,
      "graceAllowance": 1,
      "graceAllowanceCooldown": -1.0,
      "gracePeriod": 10.0,
      "graceCooloffScale": 80.0,
      "graceWarnings": [
        "@GraceWarnings_IllegalVehicleTowing_001"],
      "displayGraceTime": 1,
      "escalatedPaymentFineMultiplier": 512.0,
      "earlyPaymentPeriod": 168.0,
      "lifetime": 168.0,
      "coolOffTime": -1.0,
      "pressChargesNotificationTime": -1.0,
      "removeTimeSeconds": -1.0,
      "felonyMerits": -1,
      "ignoreIfAgainstPartyMember": 1,
      "hideCrimeNotification": -1,
      "hideCrimeInJournal": -1}}}