{
  "_RecordName_": "Character.GENHPTCHAT02",
  "_RecordId_": "862c6f29-d2cc-48d8-9843-f1c5aba40e7a",
  "_RecordTag_": "Unknown",
  "_RecordValue_": {
    "_Type_": "Character",
    "characterPersonalData": {
      "_Type_": "CharacterPersonalData",
      "title": "",
      "firstName": "",
      "nickName": "",
      "lastName": "",
      "randomNameParams": null,
      "affiliation": "",
      "details": ""},
    "audioSwitchStateName": "",
    "animationRemapAlias": "",
    "characterMannequinTag": "",
    "styleMannequinTag": "",
    "combatStyle": "NotSet",
    "gender": "NotSet",
    "characterSpeedOverrides": [],
    "nicknameChance": 0.0,
    "name": "GENHPTCHAT02"}}