{
  "_RecordName_": "LootArchetypeV3Record.V3LootArchetype_Armour_Light",
  "_RecordId_": "fec30d1a-02d6-4398-bef7-7d1b4f44d7d0",
  "_RecordTag_": "Unknown",
  "_RecordValue_": {
    "_Type_": "LootArchetypeV3Record",
    "lootArchetype": {
      "_Type_": "LootArchetypeV3",
      "entries": [
        {
          "_Type_": "LootArchetypeV3Entry",
          "name": "Light armour",
          "weight": 1.0,
          "selector": {
            "_Type_": "LootArchetypeV3Selector_Tags",
            "tags": {
              "_Type_": "TagsDNFTerm",
              "positiveTags": [
                {
                  "_RecordPath_": "file://./../../../../../libs/foundry/records/tagdatabase/tagdatabase.tagdatabase.json",
                  "_RecordName_": "Tag.41aa0984-180e-4af0-9f40-d34a5b01c683",
                  "_RecordId_": "41aa0984-180e-4af0-9f40-d34a5b01c683"}],
              "negativeTags": [
                {
                  "_RecordPath_": "file://./../../../../../libs/foundry/records/tagdatabase/tagdatabase.tagdatabase.json",
                  "_RecordName_": "Tag.df996c18-51ac-405a-9422-6f22ad5a5904",
                  "_RecordId_": "df996c18-51ac-405a-9422-6f22ad5a5904"},
                {
                  "_RecordPath_": "file://./../../../../../libs/foundry/records/tagdatabase/tagdatabase.tagdatabase.json",
                  "_RecordName_": "Tag.3521eb58-d811-4f98-893a-3a4bc346fb34",
                  "_RecordId_": "3521eb58-d811-4f98-893a-3a4bc346fb34"}]}},
          "optionalData": []}]}}}