{
  "_RecordName_": "Character.CrusaderSecurity_Pilot",
  "_RecordId_": "9f35e545-3732-48b0-ac93-f9cc6f3ad19e",
  "_RecordTag_": "Unknown",
  "_RecordValue_": {
    "_Type_": "Character",
    "characterPersonalData": {
      "_Type_": "CharacterPersonalData",
      "title": "",
      "firstName": "",
      "nickName": "",
      "lastName": "",
      "randomNameParams": "file://./../../../../../../libs/foundry/records/characternamedata/humanmale.json",
      "affiliation": "",
      "details": ""},
    "audioSwitchStateName": "",
    "animationRemapAlias": "",
    "characterMannequinTag": "",
    "styleMannequinTag": "",
    "combatStyle": "NotSet",
    "gender": "Male",
    "characterSpeedOverrides": [],
    "nicknameChance": 0.0,
    "name": ""}}